{
  "name": "remote-angular",
  "shared": [
    {
      "packageName": "@angular/animations",
      "outFileName": "_angular_animations.ER3diy0Obn.js",
      "requiredVersion": "^21.0.0",
      "singleton": true,
      "strictVersion": true,
      "version": "21.2.6"
    },
    {
      "packageName": "@angular/animations/browser",
      "outFileName": "_angular_animations_browser.Mj-aN7FSrd.js",
      "requiredVersion": "^21.0.0",
      "singleton": true,
      "strictVersion": true,
      "version": "21.2.6"
    },
    {
      "packageName": "@angular/common",
      "outFileName": "_angular_common.YQxwt6RKOy.js",
      "requiredVersion": "^21.0.0",
      "singleton": true,
      "strictVersion": true,
      "version": "21.2.6"
    },
    {
      "packageName": "@angular/common/http",
      "outFileName": "_angular_common_http.U8RKAF4654.js",
      "requiredVersion": "^21.0.0",
      "singleton": true,
      "strictVersion": true,
      "version": "21.2.6"
    },
    {
      "packageName": "@angular/compiler",
      "outFileName": "_angular_compiler.S_lUMNocni.js",
      "requiredVersion": "^21.0.0",
      "singleton": true,
      "strictVersion": true,
      "version": "21.2.6"
    },
    {
      "packageName": "@angular/core",
      "outFileName": "_angular_core.WVpYbCTfgh.js",
      "requiredVersion": "^21.0.0",
      "singleton": true,
      "strictVersion": true,
      "version": "21.2.6"
    },
    {
      "packageName": "@angular/core/event-dispatch-contract.min.js",
      "outFileName": "_angular_core_event_dispatch_contract_min_js.wThQhOSAmb.js",
      "requiredVersion": "^21.0.0",
      "singleton": true,
      "strictVersion": true,
      "version": "21.2.6"
    },
    {
      "packageName": "@angular/core/primitives/di",
      "outFileName": "_angular_core_primitives_di._RKVrXGWl-.js",
      "requiredVersion": "^21.0.0",
      "singleton": true,
      "strictVersion": true,
      "version": "21.2.6"
    },
    {
      "packageName": "@angular/core/primitives/event-dispatch",
      "outFileName": "_angular_core_primitives_event_dispatch.mYAzb8I7bk.js",
      "requiredVersion": "^21.0.0",
      "singleton": true,
      "strictVersion": true,
      "version": "21.2.6"
    },
    {
      "packageName": "@angular/core/primitives/signals",
      "outFileName": "_angular_core_primitives_signals.JyRUqa2c45.js",
      "requiredVersion": "^21.0.0",
      "singleton": true,
      "strictVersion": true,
      "version": "21.2.6"
    },
    {
      "packageName": "@angular/core/rxjs-interop",
      "outFileName": "_angular_core_rxjs_interop.-GuLmPkiYT.js",
      "requiredVersion": "^21.0.0",
      "singleton": true,
      "strictVersion": true,
      "version": "21.2.6"
    },
    {
      "packageName": "@angular/forms",
      "outFileName": "_angular_forms.xCWhDJfVzP.js",
      "requiredVersion": "^21.0.0",
      "singleton": true,
      "strictVersion": true,
      "version": "21.2.6"
    },
    {
      "packageName": "@angular/forms/signals",
      "outFileName": "_angular_forms_signals.bIzM2_QN7g.js",
      "requiredVersion": "^21.0.0",
      "singleton": true,
      "strictVersion": true,
      "version": "21.2.6"
    },
    {
      "packageName": "@angular/forms/signals/compat",
      "outFileName": "_angular_forms_signals_compat.-k4QPnBn7n.js",
      "requiredVersion": "^21.0.0",
      "singleton": true,
      "strictVersion": true,
      "version": "21.2.6"
    },
    {
      "packageName": "@angular/platform-browser",
      "outFileName": "_angular_platform_browser.AU_1zXqIbV.js",
      "requiredVersion": "^21.0.0",
      "singleton": true,
      "strictVersion": true,
      "version": "21.2.6"
    },
    {
      "packageName": "@angular/platform-browser/animations",
      "outFileName": "_angular_platform_browser_animations.NNC3S9-rN3.js",
      "requiredVersion": "^21.0.0",
      "singleton": true,
      "strictVersion": true,
      "version": "21.2.6"
    },
    {
      "packageName": "@angular/platform-browser/animations/async",
      "outFileName": "_angular_platform_browser_animations_async.GMJ-4maoQq.js",
      "requiredVersion": "^21.0.0",
      "singleton": true,
      "strictVersion": true,
      "version": "21.2.6"
    },
    {
      "packageName": "@angular/platform-browser-dynamic",
      "outFileName": "_angular_platform_browser_dynamic.oTLVqMi69c.js",
      "requiredVersion": "^21.0.0",
      "singleton": true,
      "strictVersion": true,
      "version": "21.2.6"
    },
    {
      "packageName": "@angular/router",
      "outFileName": "_angular_router.OWCM_cJ1TK.js",
      "requiredVersion": "^21.0.0",
      "singleton": true,
      "strictVersion": true,
      "version": "21.2.6"
    },
    {
      "packageName": "@mfe-playground/auth",
      "outFileName": "_mfe_playground_auth.L-4TvFG72b.js",
      "requiredVersion": "*",
      "singleton": true,
      "strictVersion": true,
      "version": "1.0.0"
    },
    {
      "packageName": "rxjs",
      "outFileName": "rxjs.8q0Ayj4zpB.js",
      "requiredVersion": "^7.8.0",
      "singleton": true,
      "strictVersion": true,
      "version": "7.8.2"
    },
    {
      "packageName": "rxjs/operators",
      "outFileName": "rxjs_operators.V2jnJniNsi.js",
      "requiredVersion": "^7.8.0",
      "singleton": true,
      "strictVersion": true,
      "version": "7.8.2"
    },
    {
      "packageName": "tslib",
      "outFileName": "tslib.ikbNwi3JqP.js",
      "requiredVersion": "^2.8.0",
      "singleton": true,
      "strictVersion": true,
      "version": "2.8.1"
    },
    {
      "singleton": false,
      "strictVersion": false,
      "version": "0.0.0",
      "requiredVersion": "0.0.0",
      "packageName": "@nf-internal/chunk-JSPZQF2K",
      "outFileName": "chunk-JSPZQF2K.js"
    },
    {
      "singleton": false,
      "strictVersion": false,
      "version": "0.0.0",
      "requiredVersion": "0.0.0",
      "packageName": "@nf-internal/chunk-5WQ4UZB3",
      "outFileName": "chunk-5WQ4UZB3.js"
    },
    {
      "singleton": false,
      "strictVersion": false,
      "version": "0.0.0",
      "requiredVersion": "0.0.0",
      "packageName": "@nf-internal/chunk-7ASIJKSU",
      "outFileName": "chunk-7ASIJKSU.js"
    },
    {
      "singleton": false,
      "strictVersion": false,
      "version": "0.0.0",
      "requiredVersion": "0.0.0",
      "packageName": "@nf-internal/chunk-TTQURMXB",
      "outFileName": "chunk-TTQURMXB.js"
    },
    {
      "singleton": false,
      "strictVersion": false,
      "version": "0.0.0",
      "requiredVersion": "0.0.0",
      "packageName": "@nf-internal/chunk-PIMAPNAI",
      "outFileName": "chunk-PIMAPNAI.js"
    },
    {
      "singleton": false,
      "strictVersion": false,
      "version": "0.0.0",
      "requiredVersion": "0.0.0",
      "packageName": "@nf-internal/chunk-4WKBVEGY",
      "outFileName": "chunk-4WKBVEGY.js"
    },
    {
      "singleton": false,
      "strictVersion": false,
      "version": "0.0.0",
      "requiredVersion": "0.0.0",
      "packageName": "@nf-internal/chunk-RDF3I7Y7",
      "outFileName": "chunk-RDF3I7Y7.js"
    },
    {
      "singleton": false,
      "strictVersion": false,
      "version": "0.0.0",
      "requiredVersion": "0.0.0",
      "packageName": "@nf-internal/chunk-LJJRK7ZG",
      "outFileName": "chunk-LJJRK7ZG.js"
    },
    {
      "singleton": false,
      "strictVersion": false,
      "version": "0.0.0",
      "requiredVersion": "0.0.0",
      "packageName": "@nf-internal/chunk-NRVCXPBY",
      "outFileName": "chunk-NRVCXPBY.js"
    },
    {
      "singleton": false,
      "strictVersion": false,
      "version": "0.0.0",
      "requiredVersion": "0.0.0",
      "packageName": "@nf-internal/chunk-RKEUQMMB",
      "outFileName": "chunk-RKEUQMMB.js"
    },
    {
      "singleton": false,
      "strictVersion": false,
      "version": "0.0.0",
      "requiredVersion": "0.0.0",
      "packageName": "@nf-internal/chunk-ZNT5HOY3",
      "outFileName": "chunk-ZNT5HOY3.js"
    },
    {
      "singleton": false,
      "strictVersion": false,
      "version": "0.0.0",
      "requiredVersion": "0.0.0",
      "packageName": "@nf-internal/chunk-4CLCTAJ7",
      "outFileName": "chunk-4CLCTAJ7.js"
    },
    {
      "packageName": "@mfe-playground/auth",
      "outFileName": "_mfe_playground_auth-5HUYSJF6.js",
      "requiredVersion": "",
      "singleton": true,
      "strictVersion": false,
      "version": ""
    }
  ],
  "exposes": [
    {
      "key": "./Component",
      "outFileName": "Component-QZYMOHBU.js"
    }
  ]
}